{
    "global": {
        "borderSize": 400,
        "splitterSize": 4,
        "enableRenderOnDemand": true
    },
    "borders": [
        {
            "type": "border",
            "location": "bottom",
            "children": [
                {
                    "type": "tab",
                    "enableClose": false,
                    "name": "CommandCenter",
                    "component": "CommandCenter"
                }
            ]
        },
        {
            "type": "border",
            "location": "right",
            "children": [
                {
                    "type": "tab",
                    "name": "LightPresets",
                    "component": "LightPresets",
                    "enableClose": false
                },
                {
                    "type": "tab",
                    "name": "PosPresets",
                    "component": "PosPresets",
                    "enableClose": false
                },
                {
                    "type": "tab",
                    "name": "Effect",
                    "component": "EffectList",
                    "enableClose": false
                }
            ]
        }
    ],
    "layout": {
        "type": "row",
        "children": [
            {
                "type": "row",
                "children": [
                    {
                        "type": "row",
                        "weight": 80,
                        "children": [
                            {
                                "type": "tabset",
                                "selected": 0,
                                "enableMaximize": true,
                                "children": [
                                    {
                                        "type": "tab",
                                        "name": "Simulator",
                                        "component": "Simulator",
                                        "enableClose": false
                                    },
                                    {
                                        "type": "tab",
                                        "name": "Three Simulator",
                                        "component": "ThreeSimulator",
                                        "enableClose": false
                                    }
                                ]
                            }
                        ]
                    },
                    {
                        "type": "row",
                        "weight": 19.5,
                        "children": [
                            {
                                "type": "tabset",
                                "selected": 0,
                                "enableMaximize": false,
                                "enableTabStrip": false,
                                "enableDrop": false,
                                "enableDrag": false,
                                "enableSplit": false,
                                "children": [
                                    {
                                        "type": "tab",
                                        "name": "Wavesurfer",
                                        "component": "Wavesurfer",
                                        "enableClose": false
                                    }
                                ]
                            }
                        ]
                    }
                ]
            },
            {
                "type": "tabset",
                "weight": 25,
                "selected": 0,
                "enableMaximize": false,
                "children": [
                    {
                        "type": "tab",
                        "name": "LightEditor",
                        "component": "LightEditor",
                        "enableClose": false
                    },
                    {
                        "type": "tab",
                        "name": "PosEditor",
                        "component": "PosEditor",
                        "enableClose": false
                    }
                ]
            }
        ]
    }
}
